{
	"1": {
		"collection_date": "05-2020",
		"age": "-",
		"sex": "-",
		"platform": "Illumina NextSeq 500"
	},
	"2": {
		"collection_date": "05-2020",
		"age": "-",
		"sex": "-",
		"platform": "Illumina NextSeq 500"
	},
	"3": {
		"collection_date": "05-2020",
		"age": "-",
		"sex": "-",
		"platform": "Illumina NextSeq 500"
	},
	"4": {
		"collection_date": "05-2020",
		"age": "-",
		"sex": "-",
		"platform": "Illumina NextSeq 500"
	},
	"6": {
		"collection_date": "05-2020",
		"age": "-",
		"sex": "-",
		"platform": "Illumina NextSeq 500"
	},
	"7": {
		"collection_date": "05-2020",
		"age": "-",
		"sex": "-",
		"platform": "Illumina NextSeq 500"
	},
	"9": {
		"collection_date": "05-2020",
		"age": "-",
		"sex": "-",
		"platform": "Illumina NextSeq 500"
	},
	"10": {
		"collection_date": "05-2020",
		"age": "-",
		"sex": "-",
		"platform": "Illumina NextSeq 500"
	},
	"11": {
		"collection_date": "05-2020",
		"age": "-",
		"sex": "-",
		"platform": "Illumina NextSeq 500"
	},
	"13": {
		"collection_date": "05-2020",
		"age": "-",
		"sex": "-",
		"platform": "Illumina NextSeq 500"
	},
	"14": {
		"collection_date": "05-2020",
		"age": "-",
		"sex": "-",
		"platform": "Illumina NextSeq 500"
	},
	"16": {
		"collection_date": "05-2020",
		"age": "-",
		"sex": "-",
		"platform": "Illumina NextSeq 500"
	},
	"18": {
		"collection_date": "05-2020",
		"age": "-",
		"sex": "-",
		"platform": "Illumina NextSeq 500"
	},
	"19": {
		"collection_date": "05-2020",
		"age": "-",
		"sex": "-",
		"platform": "Illumina NextSeq 500"
	},
	"20": {
		"collection_date": "05-2020",
		"age": "-",
		"sex": "-",
		"platform": "Illumina NextSeq 500"
	},
	"21": {
		"collection_date": "05-2020",
		"age": "-",
		"sex": "-",
		"platform": "Illumina NextSeq 500"
	},
	"22": {
		"collection_date": "05-2020",
		"age": "-",
		"sex": "-",
		"platform": "Illumina NextSeq 500"
	},
	"26": {
		"collection_date": "05-2020",
		"age": "-",
		"sex": "-",
		"platform": "Illumina NextSeq 500"
	},
	"29": {
		"collection_date": "05-2020",
		"age": "-",
		"sex": "-",
		"platform": "Illumina NextSeq 500"
	},
	"30": {
		"collection_date": "05-2020",
		"age": "-",
		"sex": "-",
		"platform": "Illumina NextSeq 500"
	},
	"31": {
		"collection_date": "05-2020",
		"age": "-",
		"sex": "-",
		"platform": "Illumina NextSeq 500"
	},
	"32": {
		"collection_date": "05-2020",
		"age": "-",
		"sex": "-",
		"platform": "Illumina NextSeq 500"
	},
	"38": {
		"collection_date": "05-2020",
		"age": "-",
		"sex": "-",
		"platform": "Illumina NextSeq 500"
	}
}